Metadata-Version: 1.0
Name: easy-ansible
Version: 1.0.1
Summary: An ansible api that can be used directly and easily
Home-page: https://github.com/CcccFz/easy-ansible
Author: CcccFz
Author-email: ccccfz@163.com
License: UNKNOWN
Platform: UNKNOWN
